fpt_api/__init__.py
fpt_api/fpt_api.py
fpt_api-0.3.5.dist-info/LICENSE
fpt_api-0.3.5.dist-info/METADATA
fpt_api-0.3.5.dist-info/WHEEL
fpt_api-0.3.5.dist-info/top_level.txt
fpt_api-0.3.5.dist-info/RECORD
