Metadata-Version: 2.2
Name: fpt-api
Version: 0.3.5
Summary: A thread-safe wrapper around Flow Production Tracking (formerly ShotGrid) with query field support
Home-page: https://github.com/ksallee/fpt-api
Author: Kevin Sallee
Author-email: kevin.sallee@gmail.com
Classifier: Development Status :: 3 - Alpha
Classifier: Intended Audience :: Developers
Classifier: License :: OSI Approved :: GNU General Public License v3 (GPLv3)
Classifier: Programming Language :: Python :: 3
Classifier: Programming Language :: Python :: 3.7
Classifier: Programming Language :: Python :: 3.8
Classifier: Programming Language :: Python :: 3.9
Classifier: Programming Language :: Python :: 3.10
Requires-Python: >=3.7
License-File: LICENSE
Requires-Dist: shotgun_api3
Requires-Dist: urllib3
Requires-Dist: certifi
Requires-Dist: requests
Dynamic: author
Dynamic: author-email
Dynamic: classifier
Dynamic: description
Dynamic: description-content-type
Dynamic: home-page
Dynamic: requires-dist
Dynamic: requires-python
Dynamic: summary
